{
  "cssFiles": [
    "src/app/admin-day-theme.css",
    "src/app/admin-gallery.css",
    "src/app/admin-key-dates-reference.css",
    "src/app/admin-news-reference.css",
    "src/app/admin-payment-detail.css",
    "src/app/admin-payments-reference.css",
    "src/app/admin-ticker-reference.css",
    "src/app/admin-typography.css",
    "src/app/admin-units-reference.css",
    "src/app/admin-user-detail.css",
    "src/app/admin-users-reference.css",
    "src/app/army-design.css",
    "src/app/cinematic-tactical.css",
    "src/app/daylight-theme.css",
    "src/app/event-support.css",
    "src/app/exercise-contour.css",
    "src/app/forest-card-carousel.css",
    "src/app/globals.css",
    "src/app/paf-theme.css",
    "src/app/participant-dashboard.css",
    "src/app/participant-panel.css",
    "src/app/participant-portal-day.css",
    "src/app/participation-confirm.css",
    "src/app/pats-awards-showcase.css",
    "src/app/pats-card-surface.css",
    "src/app/pats-design-system.css",
    "src/app/pats-footer-viewport.css",
    "src/app/pats-forest-cards.css",
    "src/app/pats-hero.css",
    "src/app/pats-home-day.css",
    "src/app/pats-inner-pages.css",
    "src/app/pats-mission-showcase.css",
    "src/app/pats-motion.css",
    "src/app/pats-navigation.css",
    "src/app/pats-portal.css",
    "src/app/pats-refresh.css",
    "src/app/pats-responsive.css",
    "src/app/pats-section-panels.css",
    "src/app/pats-section-spacing.css",
    "src/app/pats-site-chrome.css",
    "src/app/pats-typography.css",
    "src/app/pats-video-gallery.css",
    "src/app/pats-zebra.css",
    "src/app/payment-status-timeline.css",
    "src/app/portal-design.css",
    "src/app/tac-edition-timeline.css",
    "src/app/tac-mission-card.css",
    "src/app/team-members.css"
  ],
  "importantCount": 2375,
  "importantByFile": {
    "src/app/admin-day-theme.css": 289,
    "src/app/admin-gallery.css": 0,
    "src/app/admin-key-dates-reference.css": 5,
    "src/app/admin-news-reference.css": 8,
    "src/app/admin-payment-detail.css": 0,
    "src/app/admin-payments-reference.css": 86,
    "src/app/admin-ticker-reference.css": 24,
    "src/app/admin-typography.css": 39,
    "src/app/admin-units-reference.css": 18,
    "src/app/admin-user-detail.css": 13,
    "src/app/admin-users-reference.css": 151,
    "src/app/army-design.css": 0,
    "src/app/cinematic-tactical.css": 3,
    "src/app/daylight-theme.css": 416,
    "src/app/event-support.css": 0,
    "src/app/exercise-contour.css": 80,
    "src/app/forest-card-carousel.css": 10,
    "src/app/globals.css": 46,
    "src/app/paf-theme.css": 9,
    "src/app/participant-dashboard.css": 26,
    "src/app/participant-panel.css": 93,
    "src/app/participant-portal-day.css": 75,
    "src/app/participation-confirm.css": 41,
    "src/app/pats-awards-showcase.css": 25,
    "src/app/pats-card-surface.css": 32,
    "src/app/pats-design-system.css": 13,
    "src/app/pats-footer-viewport.css": 13,
    "src/app/pats-forest-cards.css": 19,
    "src/app/pats-hero.css": 6,
    "src/app/pats-home-day.css": 90,
    "src/app/pats-inner-pages.css": 46,
    "src/app/pats-mission-showcase.css": 23,
    "src/app/pats-motion.css": 29,
    "src/app/pats-navigation.css": 28,
    "src/app/pats-portal.css": 42,
    "src/app/pats-refresh.css": 282,
    "src/app/pats-responsive.css": 13,
    "src/app/pats-section-panels.css": 55,
    "src/app/pats-section-spacing.css": 19,
    "src/app/pats-site-chrome.css": 12,
    "src/app/pats-typography.css": 34,
    "src/app/pats-video-gallery.css": 11,
    "src/app/pats-zebra.css": 5,
    "src/app/payment-status-timeline.css": 0,
    "src/app/portal-design.css": 84,
    "src/app/tac-edition-timeline.css": 21,
    "src/app/tac-mission-card.css": 12,
    "src/app/team-members.css": 29
  },
  "cssImports": [
    "src/app/(admin)/admin/gallery/page.tsx -> @/app/admin-gallery.css",
    "src/app/(admin)/admin/key-dates/page.tsx -> @/app/admin-key-dates-reference.css",
    "src/app/(admin)/admin/layout.tsx -> @/app/admin-typography.css",
    "src/app/(admin)/admin/news/[id]/edit/page.tsx -> @/app/admin-news-reference.css",
    "src/app/(admin)/admin/news/[id]/edit/page.tsx -> @/app/admin-user-detail.css",
    "src/app/(admin)/admin/news/new/page.tsx -> @/app/admin-news-reference.css",
    "src/app/(admin)/admin/news/new/page.tsx -> @/app/admin-user-detail.css",
    "src/app/(admin)/admin/news/page.tsx -> @/app/admin-news-reference.css",
    "src/app/(admin)/admin/news/page.tsx -> @/app/admin-users-reference.css",
    "src/app/(admin)/admin/payments/[id]/page.tsx -> @/app/admin-payment-detail.css",
    "src/app/(admin)/admin/payments/[id]/page.tsx -> @/app/admin-user-detail.css",
    "src/app/(admin)/admin/payments/[id]/page.tsx -> @/app/payment-status-timeline.css",
    "src/app/(admin)/admin/payments/page.tsx -> @/app/admin-payments-reference.css",
    "src/app/(admin)/admin/ticker/[id]/edit/page.tsx -> @/app/admin-ticker-reference.css",
    "src/app/(admin)/admin/ticker/[id]/edit/page.tsx -> @/app/admin-user-detail.css",
    "src/app/(admin)/admin/ticker/new/page.tsx -> @/app/admin-ticker-reference.css",
    "src/app/(admin)/admin/ticker/new/page.tsx -> @/app/admin-user-detail.css",
    "src/app/(admin)/admin/ticker/page.tsx -> @/app/admin-ticker-reference.css",
    "src/app/(admin)/admin/tickets/[id]/page.tsx -> @/app/admin-user-detail.css",
    "src/app/(admin)/admin/tickets/page.tsx -> @/app/admin-payments-reference.css",
    "src/app/(admin)/admin/tickets/page.tsx -> @/app/admin-users-reference.css",
    "src/app/(admin)/admin/units/page.tsx -> @/app/admin-units-reference.css",
    "src/app/(admin)/admin/user-management/page.tsx -> @/app/admin-users-reference.css",
    "src/app/(admin)/admin/users/[id]/page.tsx -> @/app/admin-user-detail.css",
    "src/app/(admin)/admin/users/page.tsx -> @/app/admin-users-reference.css",
    "src/app/(dashboard)/event/dashboard/page.tsx -> @/app/payment-status-timeline.css",
    "src/app/(dashboard)/event/payment/page.tsx -> @/app/payment-status-timeline.css",
    "src/app/layout.tsx -> ./globals.css",
    "src/components/admin/PaymentReviewPanel.tsx -> @/app/admin-payment-detail.css",
    "src/components/admin/PaymentReviewPanel.tsx -> @/app/payment-status-timeline.css",
    "src/components/dashboard/ParticipationConfirmCard.tsx -> @/app/participation-confirm.css",
    "src/components/dashboard/PaymentSubmissionForm.tsx -> @/app/payment-status-timeline.css",
    "src/components/payments/PaymentStatusTimeline.tsx -> @/app/payment-status-timeline.css",
    "src/css.d.ts -> @/app/foo.css"
  ],
  "hexInTsx": 95
}
